precommit_message_preservation/__init__.py
precommit_message_preservation/py.typed
precommit_message_preservation-1.3.dist-info/LICENSE
precommit_message_preservation-1.3.dist-info/METADATA
precommit_message_preservation-1.3.dist-info/WHEEL
precommit_message_preservation-1.3.dist-info/entry_points.txt
precommit_message_preservation-1.3.dist-info/top_level.txt
precommit_message_preservation-1.3.dist-info/RECORD
