Metadata-Version: 2.1
Name: precommit-message-preservation
Version: 1.3
Summary: A library for preserving and restoring commit messages
Home-page: https://github.com/EliRibble/precommit-message-preservation
Author: Eli Ribble
Author-email: eliribble@google.com
License: UNKNOWN
Platform: UNKNOWN
Requires-Python: >=3.6
Provides-Extra: develop
Requires-Dist: nose2 ; extra == 'develop'
Requires-Dist: twine ; extra == 'develop'
Requires-Dist: wheel ; extra == 'develop'
